pennylane_quantuminspire/__init__.py
pennylane_quantuminspire/cqasm.py
pennylane_quantuminspire/qi_device.py
pennylane_quantuminspire/qi_instructions.py
pennylane_quantuminspire-0.12.0.dist-info/LICENSE
pennylane_quantuminspire-0.12.0.dist-info/METADATA
pennylane_quantuminspire-0.12.0.dist-info/WHEEL
pennylane_quantuminspire-0.12.0.dist-info/RECORD
