Metadata-Version: 2.1
Name: pennylane-quantuminspire
Version: 0.12.0
Summary: The PennyLane-QuantumInspire plugin integrates the Quantum Inspire quantum computing backends with PennyLane's quantum machine learning capabilities.
Home-page: https://www.quantum-inspire.com
Author: Quantum Inspire
Author-email: support@quantum-inspire.com
Requires-Python: >=3.11,<3.14
Classifier: Development Status :: 4 - Beta
Classifier: License :: OSI Approved :: Apache Software License
Classifier: Programming Language :: Python :: 3
Classifier: Programming Language :: Python :: 3.11
Classifier: Programming Language :: Python :: 3.12
Classifier: Programming Language :: Python :: 3.13
Requires-Dist: opensquirrel (>=0.8.0,<0.9.0)
Requires-Dist: pennylane (>=0.43.0,<0.44.0)
Requires-Dist: pennylane-qiskit (>=0.43.0,<0.44.0)
Requires-Dist: qiskit-quantuminspire (>=0.16.0,<0.17.0)
Project-URL: Documentation, https://qutech-delft.github.io/pennylane-quantuminspire/
Project-URL: Repository, https://github.com/qutech-delft/pennylane-quantuminspire
